<?xml version="1.0" encoding="windows-1251" standalone="yes"?>
<Paths>
	<!-- Начальный ролик. Текст на чёрном фоне. -->
	<Path Name = "start_game">
		<Point  coord="0 0 0" rotation="0 0 0 1"/>   
	</Path>

	<!-- Опенинг. Лиса ездит по Краю, потом разговор с отцом в Глухом. -->
	<Path Name = "OpeningOpen">
		<Point  coord="1120.973 317.971 2883.776" rotation="-0.081 0.518 -0.049 0.850"/>
		<Point  coord="1137.537 317.971 2958.951" rotation="-0.062 0.714 -0.063 0.695"/>
   </Path>

   <Path Name = "OpeningOpen2">
	   <Point  coord="1914.485 321.752 827.426" rotation="-0.090 -0.541 0.059 0.834"/>
	   <Point  coord="1914.485 321.752 827.426" rotation="0.012 0.911 -0.026 -0.412"/>
   </Path>

   <Path Name = "Opening1">
		<Point  coord="495.108 293.732 390.902" rotation="-0.005 0.890 0.009 -0.455"/>
		<Point  coord="495.108 293.732 390.902" rotation="-0.001 -0.427 0.001 0.904"/>
   </Path>

   <Path Name = "Opening11">
	   <Point  coord="803.747 301.765 620.645" rotation="-0.070 0.575 -0.049 0.813"/>
	   <Point  coord="803.747 301.765 620.645" rotation="-0.004 -0.038 0.000 0.999"/>
   </Path>

   <Path Name = "Opening2">
	   <Point  coord="456.295 307.974 1832.341" rotation="0.031 0.928 -0.080 -0.363"/>
	   <Point  coord="456.716 307.867 1831.885" rotation="0.023 0.927 -0.057 -0.369"/>
   </Path>

   <Path Name = "Opening22">
	   <Point  coord="2512.513 345.541 1753.524" rotation="-0.005 0.994 -0.093 0.056"/>
	   <Point  coord="2512.513 345.541 1753.524" rotation="0.012 0.922 -0.028 -0.385"/>
   </Path>

   <Path Name = "Opening3">
	   <Point  coord="1123.271 332.014 1279.940" rotation="-0.131 -0.071 0.009 0.989"/>
	   <Point  coord="1152.514 304.625 1427.074" rotation="-0.022 -0.097 0.002 0.995"/>
	   <Point  coord="1177.595 302.255 1556.238" rotation="-0.006 -0.094 0.001 0.996"/>
	   <Point  coord="1192.534 301.410 1631.562" rotation="-0.004 -0.106 0.000 0.994"/>
	   <Point  coord="1215.236 301.799 1705.708" rotation="-0.013 -0.130 0.002 0.991"/>
   </Path>

   <Path Name = "Opening4">
	   <Point  coord="2191.357 494.434 2938.922" rotation="-0.071 0.921 -0.325 0.202"/>
	   <Point  coord="2036.259 494.434 2942.350" rotation="0.104 0.894 -0.338 -0.274"/>
   </Path>

   <Path Name = "Opening5">
	   <Point  coord="1198.445 316.301 2707.351" rotation="-0.133 -0.399 0.058 0.905"/>
	   <Point  coord="1145.808 316.301 2800.191" rotation="-0.053 -0.684 0.050 0.726"/>
	   <Point  coord="1160.251 316.301 2892.039" rotation="-0.042 -0.848 0.068 0.525"/>
   </Path>

	<Path Name = "Opening_End">
		<Point  coord="1160.251 316.301 2892.039" rotation="-0.042 -0.848 0.068 0.525"/>
		<Point  coord="1278.718 298.366 2848.238" rotation="-0.031 -0.820 0.044 0.569"/>
		<Point  coord="1598.081 321.700 2727.021" rotation="0.017 -0.824 -0.025 0.566"/>
		<Point  coord="1836.623 328.474 2627.243" rotation="-0.033 -0.862 0.057 0.502"/>
		<Point  coord="1883.424 324.439 2594.026" rotation="0.004 0.973 -0.018 -0.228"/>
		<Point  coord="1919.835 326.524 2472.173" rotation="-0.013 0.879 0.024 -0.476"/>
		<Point  coord="1998.332 331.209 2430.635" rotation="0.015 -0.768 -0.018 0.641"/>
		<Point  coord="2062.536 333.930 2422.305" rotation="-0.023 0.950 0.071 -0.303"/>
		<Point  coord="2101.423 350.460 2351.098" rotation="-0.015 0.963 0.056 -0.264"/>
		<Point  coord="2141.596 355.971 2297.533" rotation="0.001 -0.665 -0.001 0.747"/>
		<Point  coord="2297.435 358.093 2335.318" rotation="-0.005 -0.621 0.004 0.784"/>
		<Point  coord="2425.023 362.975 2330.354" rotation="0.006 -0.752 -0.007 0.659"/>
		<Point  coord="2839.070 363.540 2311.997" rotation="-0.008 -0.684 0.007 0.729"/>
		<Point  coord="3170.474 374.570 2536.556" rotation="0.016 -0.436 -0.008 0.900"/>
		<Point  coord="3366.887 419.581 2778.481" rotation="0.018 -0.221 -0.004 0.975"/>
		<Point  coord="3455.971 437.729 2969.287" rotation="-0.042 0.145 -0.006 0.988"/>
		<Point  coord="3520.721 429.683 3201.384" rotation="-0.033 0.479 -0.018 0.877"/>
		<Point  coord="3431.363 418.060 3285.490" rotation="-0.051 0.634 -0.042 0.770"/>
		<Point  coord="3351.999 388.020 3301.754" rotation="-0.010 0.582 -0.007 0.813"/>
	</Path>

	<Path Name = "start_rolik1">
		<Point  coord="3351.999 388.020 3301.754" rotation="-0.010 0.582 -0.007 0.813"/>   
		<Point  coord="3348.970 369.043 3302.484" rotation="0.052 0.593 0.038 0.803"/>   
	</Path>

	<Path Name = "start_rolik5">
		<Point  coord="3347.710 371.891 3285.348" rotation="-0.025 0.132 -0.003 0.991"/>   
		<Point  coord="3347.910 371.891 3285.548" rotation="-0.025 0.132 -0.003 0.991"/>   
	</Path>

	<Path Name = "start_rolik6">
		<Point  coord="3344.738 370.324 3303.042" rotation="-0.113 0.285 -0.034 0.951"/>   
		<Point  coord="3344.638 370.324 3302.942" rotation="-0.113 0.286 -0.035 0.952"/>   
	</Path>

	<Path Name = "start_rolik2">
		<Point  coord="3344.750 369.521 3303.303" rotation="0.080 0.657 0.070 0.746"/>   
		<Point  coord="3344.850 369.521 3303.403" rotation="0.080 0.657 0.070 0.746"/>   
	</Path>

	<Path Name = "start_rolik3">
		<Point  coord="3340.705 373.665 3292.612" rotation="-0.146 -0.244 0.037 0.958"/>  
		<Point  coord="3342.872 373.665 3291.333" rotation="-0.145 -0.182 0.027 0.972"/>  
	</Path>

	<Path Name = "start_rolik8">
		<Point  coord="3344.628 369.596 3305.261" rotation="0.030 0.924 0.074 0.375"/>  
		<Point  coord="3348.161 369.948 3308.872" rotation="-0.006 0.925 -0.015 0.378"/> 
	</Path>

	<Path Name = "start_rolik4">
		<Point  coord="3358.524 370.779 3276.579" rotation="-0.019 0.059 -0.001 0.998"/>  
		<Point  coord="3359.000 370.779 3277.000" rotation="-0.019 0.059 -0.001 0.998"/>
	</Path>

	<!-- Уничтожение Глухого. Тупиковая концовка. -->
	<Path Name = "AltEnding3">
		<Point  coord="3422.170 389.896 3225.362" rotation="-0.086 0.495 -0.049 0.863" 
		zoom ="1.5" />
		<Point  coord="3407.462 389.896 3206.752" rotation="-0.091 0.352 -0.034 0.931" 
		zoom ="1" />
	</Path>

	<!-- первый бандит -->

	<Path Name = "cam01">
		<Point  coord="2944.139 333.339 2370.245" rotation="0.073 0.832 0.113 0.538"/>
		<Point  coord="2950.096 334.628 2381.249" rotation="0.007 0.932 0.018 0.363"/>
	</Path>

	<Path Name = "cam01_hd">
		<Point  coord="2950.927 333.339 2380.891" rotation="0.056 0.862 0.097 0.495"/>
		<Point  coord="2956.884 337.185 2391.895" rotation="-0.061 0.899 -0.132 0.413"/>
	</Path>

	<!-- Встреча с Лисой в городе -->
	<Path Name = "lisa_cam01">
		<Point  coord="1275.287 293.238 2844.756" rotation="-0.022 0.600 -0.016 0.799"/>
		<Point  coord="1275.287 297.173 2844.756" rotation="-0.022 0.600 -0.016 0.799"/>
	</Path>

	<Path Name = "lisa_cam02">
		<Point  coord="-9.757 4.154 0.000"/>
		<Point  coord="-15.00 6.000 0.000"/>
	</Path>

	<!-- Лиса, Ржавенск -->
	<Path Name = "lisa1_cam01">
		<Point  coord="651.808 277.967 3697.396" rotation="-0.050 0.765 -0.060 0.640"/>
		<Point  coord="653.376 277.967 3673.449" rotation="-0.037 0.613 -0.029 0.788"/>
	</Path>

	<Path Name = "lisa1_cam02">
		<Point  coord="578.984 285.939 3660.240" rotation="-0.161 -0.263 0.045 0.950"/>
		<Point  coord="578.984 285.939 3660.240" rotation="-0.135 -0.327 0.047 0.934"/>
	</Path>

	<!-- Лиса, Чеснокойл -->
	<Path Name = "lisa2_cam01">
		<Point  coord="2218.447 369.736 1919.916" rotation="-0.043 0.931 -0.118 0.343"/>
		<Point  coord="2228.795 369.736 1911.091" rotation="-0.057 0.890 -0.117 0.437"/>
	</Path>

	<Path Name = "lisa2_cam02">
		<Point  coord="2140.452 376.724 1861.375" rotation="-0.122 -0.476 0.067 0.868"/>
		<Point  coord="2136.231 376.724 1870.220" rotation="-0.085 -0.546 0.056 0.832"/>
	</Path>

	<!-- Лиса, Сосновка -->
	<Path Name = "lisa3_cam01">
		<Point  coord="1636.533 318.064 2070.729" rotation="-0.056 0.867 -0.099 0.486"/>
		<Point  coord="1645.622 318.064 2055.892" rotation="-0.056 0.823 -0.082 0.560"/>
	</Path>

	<Path Name = "lisa3_cam02">
		<Point  coord="1600.795 317.105 2083.930" rotation="-0.007 0.992 -0.103 0.068"/>
		<Point  coord="1596.065 315.190 2052.868" rotation="-0.004 0.994 -0.039 0.098"/>
	</Path>

	<!-- Лиса, Старый Посёлок -->
	<Path Name = "lisa4_cam01">
		<Point  coord="1362.524 303.593 268.395" rotation="-0.119 -0.496 0.069 0.857"/>
		<Point  coord="1362.524 303.593 268.395" rotation="-0.082 -0.587 0.060 0.803"/>
	</Path>

	<Path Name = "lisa4_cam02">
		<Point  coord="1457.292 309.295 362.030" rotation="-0.031 0.958 -0.114 0.260"/>
		<Point  coord="1448.436 303.212 343.753" rotation="-0.032 0.964 -0.141 0.221"/>
	</Path>

	<!-- Лиса, Заимка -->
	<Path Name = "lisa5_cam01">
		<Point  coord="1989.807 302.758 842.544" rotation="0.008 0.696 0.008 0.718"/>
		<Point  coord="1989.761 302.758 841.095" rotation="0.008 0.692 0.008 0.722"/>
	</Path>

	<Path Name = "lisa5_cam02">
		<Point coord="1982.806 302.914 832.923" rotation="0.018 0.950 0.057 0.307"/>
		<Point coord="1980.758 302.914 834.375" rotation="0.014 0.968 0.057 0.244"/>
	</Path>

	<Path Name = "lisa5_cam03">
		<Point coord="1958.151 312.634 785.513" rotation="-0.130 -0.170 0.023 0.977"/>
		<Point coord="1971.192 312.634 783.314" rotation="-0.136 -0.015 0.002 0.991"/>
	</Path>

	<!-- Лиса, Гугулино -->
	<Path Name = "lisa6_cam01">
		<Point coord="3051.592 320.033 434.158" rotation="-0.030 -0.569 0.020 0.822"/>
		<Point coord="3056.158 320.033 421.880" rotation="-0.017 -0.578 0.012 0.816"/>
	</Path>

	<Path Name = "lisa6_cam02">
		<Point coord="3144.014 340.711 363.468" rotation="-0.121 0.178 -0.022 0.976"/>
		<Point coord="3158.825 340.862 369.741" rotation="-0.131 0.295 -0.041 0.946"/>
	</Path>

	<Path Name = "lisa6_cam03">
		<Point coord="3089.025 319.576 422.007" rotation="0.021 -0.706 -0.021 0.708"/>
		<Point coord="3088.997 319.576 431.617" rotation="0.024 -0.693 -0.023 0.720"/>
	</Path>

	<!-- Лиса, Серп и Молот -->
	<Path Name = "lisa7_cam01">
		<Point  coord="3800.384 357.907 1633.454" rotation="-0.076 0.031 -0.002 0.997"/>
		<Point  coord="3801.357 360.315 1617.869" rotation="-0.076 0.006 -0.000 0.997"/>
	</Path>

	<Path Name = "lisa7_cam02">
		<Point  coord="3784.538 353.877 1730.984" rotation="0.000 1.000 -0.022 -0.014"/>
		<Point  coord="3785.256 352.752 1706.021" rotation="-0.000 1.000 -0.009 0.002"/>
	</Path>

	<!-- Лиса, Троицкое -->
	<Path Name = "lisa8_cam01">
		<Point  coord="3176.496 328.397 1144.681" rotation="-0.087 -0.005 0.000 0.996"/>
		<Point  coord="3176.496 336.915 1144.681" rotation="-0.087 -0.005 0.000 0.996"/>
	</Path>

	<Path Name = "lisa8_cam02">
		<Point  coord="3202.996 323.166 1237.920" rotation="-0.034 0.818 -0.049 0.572"/>
		<Point  coord="3200.395 323.166 1245.148" rotation="-0.020 0.897 -0.042 0.440"/>
	</Path>

	<Path Name = "lisa8_cam021">
		<Point  coord="3171.316 349.993 1305.297" rotation="0.002 0.988 -0.151 -0.012"/>
		<Point  coord="3181.633 349.856 1303.892" rotation="-0.008 0.986 -0.157 0.053"/>
	</Path>

	<Path Name = "lisa8_cam03">
		<Point  coord="3215.562 324.523 1145.334" rotation="0.009 0.522 0.005 0.853"/>
		<Point  coord="3211.473 324.523 1137.317" rotation="0.009 0.522 0.005 0.853"/>
	</Path>

	<Path Name = "lisa8_cam04">
		<Point  coord="3185.324 321.607 1232.695" rotation="0.032 0.265 0.009 0.964"/>
		<Point  coord="3187.434 321.607 1233.964" rotation="0.026 0.325 0.009 0.945"/>
	</Path>

	<!-- Гопстоп Феликса на пути в Глухое  -->
	<Path Name = "felix1_cam01">
		<Point  coord="2014.381 322.770 2428.558" rotation="-0.030 0.700 -0.029 0.713"/>
		<Point  coord="2014.076 322.770 2438.160" rotation="-0.011 0.774 -0.014 0.633"/>
	</Path>

	<!-- Денег нет или жалко. Драка с Феликсом -->
	<Path Name = "felix1_cam02">
		<Point  coord="1973.413 322.973 2433.509" rotation="-0.062 0.807 -0.086 0.580"/>
		<Point  coord="1974.076 322.858 2431.320" rotation="-0.059 0.735 -0.064 0.673"/>
	</Path>

	<Path Name = "felix1_cam03">
		<Point  coord="1993.671 322.180 2429.792" rotation="-0.019 -0.646 0.016 0.763"/>
		<Point  coord="1997.885 323.288 2418.036" rotation="0.011 -0.620 -0.008 0.784"/>
	</Path>

	<!-- Откупились от Феликса -->
	<Path Name = "felix1_cam031">
		<Point  coord="1993.671 322.180 2429.792" rotation="-0.019 -0.646 0.016 0.763"/>
		<Point  coord="2000.527 322.519 2432.207" rotation="-0.017 -0.574 0.012 0.819"/>
	</Path>

	<Path Name = "felix1_cam04">
		<Point  coord="1962.340 325.599 2412.853" rotation="-0.008 -0.404 0.004 0.915"/>
		<Point  coord="1981.345 334.742 2455.986" rotation="-0.015 -0.855 0.024 0.518"/>
	</Path>

	<!-- ролик "умирающий отец" -->
	<Path Name = "FatherDe_cam01">
		<Point  coord="3351.284 369.726 3303.019" rotation="-0.010 0.916 0.022 -0.401"/>
		<Point  coord="3351.827 370.183 3304.411" rotation="0.011 0.925 -0.028 -0.378"/>
	</Path>

	<Path Name = "Father_cam01">
		<Point  coord="3351.807 368.527 3302.623" rotation="-0.007 -0.723 0.007 0.691"/>
		<Point  coord="3352.696 368.510 3302.582" rotation="-0.007 -0.723 0.007 0.691"/>
	</Path>

	<Path Name = "Father_cam02">
		<Point  coord="3354.282 370.407 3303.857" rotation="0.055 0.877 -0.467 -0.103"
		  speed="1"/>
		<Point  coord="3352.800 374.079 3303.618" rotation="0.304 0.696 -0.472 -0.447"
		  speed="1"/>
		<Point  coord="3345.040 389.036 3301.598" rotation="-0.394 -0.568 0.355 0.630"
		  speed="3"/>
	</Path>

	<Path Name = "Father_cam03">
		 <Point  coord="3353.614 368.587 3303.540" rotation="-0.017 0.879 0.032 -0.476"/>
		 <Point  coord="3354.031 368.623 3303.271" rotation="-0.023 0.877 0.042 -0.478"/>
	</Path>

	<Path Name = "Father_cam04">
		 <Point  coord="3350.652 376.536 3320.969" rotation="0.027 0.972 -0.135 -0.192"/>
		 <Point  coord="3342.852 376.536 3316.088" rotation="0.049 0.915 -0.117 -0.383"/>
	</Path>

	<Path Name = "Father_cam05">
		 <Point  coord="3359.908 369.002 3303.074" rotation="-0.010 0.730 -0.011 0.683"/>
		 <Point  coord="3361.545 369.051 3303.183" rotation="-0.010 0.730 -0.011 0.683"/>
	</Path>

	<Path Name = "Father_cam06">
		 <Point  coord="3352.119 374.017 3298.091" rotation="-0.358 -0.261 0.105 0.890"/>
		 <Point  coord="3350.857 374.017 3299.219" rotation="-0.342 -0.394 0.160 0.838"/>
	</Path>

	<Path Name = "Father_cam07">
		 <Point  coord="3353.699 368.914 3303.790" rotation="-0.037 0.888 0.074 -0.452"/>
		 <Point  coord="3353.362 368.914 3303.118" rotation="0.041 -0.813 -0.058 0.578"/>
	</Path>

	<!-- Приехали на базу к Феликсу мстить за Глухое -->
	<Path Name = "felix2_cam01">	
		<Point  coord="-9.000 3.000 9.000"/>
		<Point  coord="-11.000 5.500 11.000"/>
	</Path>

	<Path Name = "felix2_cam02">
		<Point  coord="444.726 314.529 1835.118" rotation="0.011 0.946 -0.033 -0.321"/>
		<Point  coord="445.197 314.497 1834.817" rotation="0.014 0.881 -0.026 -0.472"/>
	</Path>

	<!-- Победа на базе над ублюдками Феликса  -->
	<Path Name = "felix3_cam01">
		<Point  coord="-3.000 1.000 -7.000"/>
		<Point  coord="-1.000 2.500 -10.000"/>
   </Path>

	<!-- Победа над Феликсом -->
	<Path Name = "Felix4_cam01">
		<Point  coord="471.067 309.809 1815.207" rotation="-0.063 0.595 -0.047 0.800" />
		<Point  coord="471.177 309.810 1815.317" rotation="-0.063 0.595 -0.047 0.800" />
   </Path>

   <Path Name = "Felix4_cam02">
		<Point  coord="461.400 308.113 1821.075" rotation="-0.005 0.966 -0.019 0.258" />
		<Point  coord="461.710 308.114 1821.385" rotation="-0.005 0.966 -0.019 0.258" />
   </Path>

   <Path Name = "Felix4_cam03">
		<Point  coord="460.499 307.715 1816.206" rotation="0.020 -0.257 -0.005 0.966" />
		<Point  coord="460.610 307.716 1816.316" rotation="0.020 -0.257 -0.005 0.966" />
   </Path>

   <Path Name = "Felix4_cam04">
		<Point  coord="462.560 308.022 1818.758" rotation="-0.015 0.791 -0.019 0.611" />
		<Point  coord="462.770 308.023 1818.968" rotation="-0.015 0.791 -0.019 0.611" />
   </Path>

   <Path Name = "Felix4_cam05">
		<Point  coord="460.313 307.616 1818.684" rotation="0.075 -0.712 -0.077 0.694" />
		<Point  coord="460.423 307.617 1818.794" rotation="0.075 -0.712 -0.077 0.694" />
   </Path>

   <Path Name = "Felix4_cam06">
		<Point  coord="464.181 308.360 1820.729" rotation="-0.029 0.870 -0.051 0.490" />
		<Point  coord="464.391 308.361 1820.939" rotation="-0.029 0.870 -0.051 0.490" />
   </Path>

   <Path Name = "Felix4_cam07">
		<Point  coord="461.105 307.902 1817.023" rotation="0.003 -0.290 -0.001 0.957" />
		<Point  coord="461.215 307.903 1817.133" rotation="0.003 -0.290 -0.001 0.957" />
   </Path>

   <Path Name = "Felix4_cam08">
		<Point  coord="456.391 308.004 1821.860" rotation="0.010 0.895 -0.020 -0.446" />
		<Point  coord="456.501 308.005 1821.970" rotation="0.010 0.895 -0.020 -0.446" />
   </Path>

   <Path Name = "Felix4_cam09">
		<Point  coord="459.650 307.355 1815.857" rotation="0.053 -0.315 -0.017 0.948" />
		<Point  coord="459.960 307.356 1816.167" rotation="0.053 -0.315 -0.017 0.948" />
   </Path>

   <Path Name = "Felix4_cam10">
		<Point  coord="463.230 312.768 1836.694" rotation="-0.011 0.987 -0.137 0.078"/>
		<Point  coord="462.968 312.296 1835.050" rotation="-0.011 0.987 -0.137 0.078"/>
   </Path>

   <Path Name = "Felix4_cam11">
		<Point  coord="454.292 308.138 1820.751" rotation="-0.005 -0.792 0.007 0.611" />
		<Point  coord="454.402 308.139 1820.861" rotation="-0.005 -0.792 0.007 0.611" />
   </Path>

	<!-- Айвен наблюдает за ГГ, едущим в Глухое. -->
	<Path Name = "AivenRolik_cam01">
		<Point  coord="2975.290 364.329 1668.837" rotation="-0.027 0.046 -0.001 0.999"/>
		<Point  coord="2975.290 364.629 1668.837" rotation="-0.027 0.046 -0.001 0.999"/>
	</Path>

	<Path Name = "AivenRolik_cam02">
		<Point  coord="2975.290 364.629 1668.837" rotation="-0.027 0.046 -0.001 0.999"/>
		<Point  coord="2975.459 364.597 1669.798" rotation="-0.016 -0.088 0.001 0.996"/>
	</Path>

	<Path Name = "AivenRolik_cam03">
		<Point  coord="2976.785 364.626 1672.951" rotation="-0.007 0.980 -0.038 0.193"/>
		<Point  coord="2976.545 364.577 1672.365" rotation="0.001 0.981 0.003 0.195"/>
	</Path>

	<!-- Приехали в Глухое с Айвеном. Видим живого Петра. -->
	<Path Name = "AivenRolik_linkedcam">
		<Point  coord="0.000 1.000 0.000"/>
		<Point  coord="0.000 15.000 0.000"/>
	</Path>

	<Path Name = "ATGRolikCam1">
		<Point  coord="3361.109 368.986 3286.049" rotation="-0.027 0.046 -0.001 0.999"/>
		<Point  coord="3361.467 369.208 3281.931" rotation="-0.087 0.014 -0.001 0.996"/>
	</Path>

	<Path Name = "ATGRolikCam2">
		<Point  coord="3362.515 368.251 3288.867" rotation="0.002 0.998 -0.066 -0.025"/>
		<Point  coord="3362.285 368.414 3291.463" rotation="-0.001 0.991 -0.135 0.007"/>
	</Path>

	<Path Name = "ATGRolikCam3">
		<Point  coord="3329.178 372.066 3297.573" rotation="-0.030 -0.803 0.041 0.594"/>
		<Point  coord="3330.312 372.066 3301.274" rotation="-0.030 -0.803 0.041 0.594"/>
	</Path>

	<!-- Отличная концовка -->
	<Path Name = "GoodEndCam1">
		<Point  coord="3131.565 320.278 422.900" rotation="-0.021 0.829 -0.031 0.559"/>
		<Point  coord="3131.016 320.234 422.677" rotation="-0.021 0.829 -0.031 0.559"/>
	</Path>

	<Path Name = "GoodEndCam2">
		<Point  coord="3127.677 319.891 418.166" rotation="-0.032 0.766 -0.038 0.641"/>
		<Point  coord="3127.813 322.395 418.236" rotation="-0.032 0.721 -0.035 0.691"/>
	</Path>

	<Path Name = "GoodEndCam3">
		<Point  coord="3127.813 322.395 418.236" rotation="-0.032 0.721 -0.035 0.691"/>
		<Point  coord="3128.769 340.055 418.726" rotation="-0.026 0.328 -0.009 0.944"/>
	</Path>

	<Path Name = "NarratorsCam1">
		<Point  coord="1344.575 338.532 820.433" rotation="-0.000 1.000 0.006 -0.002"/>
	</Path>
</Paths>
